setup.py
prob_stat_dist/Binomialdistribution.py
prob_stat_dist/Gaussiandistribution.py
prob_stat_dist/Generaldistribution.py
prob_stat_dist/__init__.py
prob_stat_dist.egg-info/PKG-INFO
prob_stat_dist.egg-info/SOURCES.txt
prob_stat_dist.egg-info/dependency_links.txt
prob_stat_dist.egg-info/not-zip-safe
prob_stat_dist.egg-info/top_level.txt